{
  "source": "NHKONEニュース",
  "updated": "2026-01-28T21:46:56.302Z",
  "items": [
    {
      "title": "世界最大規模 海賊版サイト摘発 日本の団体が中国の運営者特定",
      "link": "https://news.web.nhk/newsweb/na/na-k10015037931000",
      "pubDate": "Thu, 29 Jan 2026 05:14:07 +0900"
    },
    {
      "title": "春闘 大手自動車メーカー労組 方針固める 要求額減らす動き",
      "link": "https://news.web.nhk/newsweb/na/na-k10015037991000",
      "pubDate": "Thu, 29 Jan 2026 05:47:54 +0900"
    },
    {
      "title": "NY市場 一時1ドル＝154円台まで値下がり “市場介入否定”で",
      "link": "https://news.web.nhk/newsweb/na/na-k10015038191000",
      "pubDate": "Thu, 29 Jan 2026 05:39:08 +0900"
    },
    {
      "title": "衆院選 争点の1つに経済財政政策 各党が具体策打ち出す",
      "link": "https://news.web.nhk/newsweb/na/na-k10015037981000",
      "pubDate": "Thu, 29 Jan 2026 05:18:03 +0900"
    },
    {
      "title": "米FRB 4会合ぶり利下げ見送り 堅調な経済踏まえ判断か",
      "link": "https://news.web.nhk/newsweb/na/na-k10015038151000",
      "pubDate": "Thu, 29 Jan 2026 06:08:12 +0900"
    },
    {
      "title": "米財務長官 市場介入を否定 「レートチェック」は言及避ける",
      "link": "https://news.web.nhk/newsweb/na/na-k10015038181000",
      "pubDate": "Thu, 29 Jan 2026 05:28:42 +0900"
    },
    {
      "title": "首都高 道路清掃入札で談合か 4社に排除措置命令の方針 公取委",
      "link": "https://news.web.nhk/newsweb/na/na-k10015038091000",
      "pubDate": "Thu, 29 Jan 2026 02:04:23 +0900"
    }
  ]
}