{
  "source": "NHKONEニュース",
  "updated": "2026-01-26T03:24:58.936Z",
  "items": [
    {
      "title": "北海道 記録的大雪でJRの運転見合わせ続く【交通影響まとめ】",
      "link": "https://news.web.nhk/newsweb/na/na-k10015035581000",
      "pubDate": "Mon, 26 Jan 2026 12:00:09 +0900"
    },
    {
      "title": "青森 平川 スノーモービルで入山の8人 午前11時前に全員が下山",
      "link": "https://news.web.nhk/newsweb/na/na-k10015035571000",
      "pubDate": "Mon, 26 Jan 2026 12:12:18 +0900"
    },
    {
      "title": "円高ドル安急速に進む 株価 1000円超の値下がり",
      "link": "https://news.web.nhk/newsweb/na/na-k10015035651000",
      "pubDate": "Mon, 26 Jan 2026 11:56:32 +0900"
    },
    {
      "title": "東大 共同研究めぐる収賄事件 別の46歳医師も書類送検",
      "link": "https://news.web.nhk/newsweb/na/na-k10015035761000",
      "pubDate": "Mon, 26 Jan 2026 11:50:17 +0900"
    },
    {
      "title": "あす衆院選公示 ポスター掲示板再利用も 各地で準備進む",
      "link": "https://news.web.nhk/newsweb/na/na-k10015035721000",
      "pubDate": "Mon, 26 Jan 2026 12:11:49 +0900"
    },
    {
      "title": "東京電力HD 今後10年間の新たな再建計画 国が認定",
      "link": "https://news.web.nhk/newsweb/na/na-k10015035661000",
      "pubDate": "Mon, 26 Jan 2026 11:00:02 +0900"
    },
    {
      "title": "金の先物価格 1オンス＝5000ドルの大台突破 NY商品取引所",
      "link": "https://news.web.nhk/newsweb/na/na-k10015035681000",
      "pubDate": "Mon, 26 Jan 2026 10:56:22 +0900"
    }
  ]
}