{
  "source": "NHKONEニュース",
  "updated": "2026-01-22T05:21:12.510Z",
  "items": [
    {
      "title": "各地で積雪急増 活発な雪雲が流れ込むおそれ 交通影響に警戒を",
      "link": "https://news.web.nhk/newsweb/na/na-k10015032321000",
      "pubDate": "Thu, 22 Jan 2026 12:03:05 +0900"
    },
    {
      "title": "山上被告 宗教社会学者との接見で「無期懲役を覚悟していた」",
      "link": "https://news.web.nhk/newsweb/na/na-k10015032591000",
      "pubDate": "Thu, 22 Jan 2026 11:58:47 +0900"
    },
    {
      "title": "立民 野田代表“中道勢力のうねりつくり出し政界再編へ”",
      "link": "https://news.web.nhk/newsweb/na/na-k10015032631000",
      "pubDate": "Thu, 22 Jan 2026 12:33:40 +0900"
    },
    {
      "title": "警察庁「ローン・オフェンダー」情報センター設置 衆院選向け",
      "link": "https://news.web.nhk/newsweb/na/na-k10015032841000",
      "pubDate": "Thu, 22 Jan 2026 14:08:12 +0900"
    },
    {
      "title": "官房長官 選挙中の偽情報など SNS運営事業者に適切な対応要請",
      "link": "https://news.web.nhk/newsweb/na/na-k10015032781000",
      "pubDate": "Thu, 22 Jan 2026 14:06:12 +0900"
    },
    {
      "title": "ネイリスト殺害事件 元交際相手面会求め 女性「会いたくない」",
      "link": "https://news.web.nhk/newsweb/na/na-k10015032661000",
      "pubDate": "Thu, 22 Jan 2026 11:55:08 +0900"
    },
    {
      "title": "東京23区 中古マンション 12月の平均価格 1億1960万円に",
      "link": "https://news.web.nhk/newsweb/na/na-k10015032621000",
      "pubDate": "Thu, 22 Jan 2026 11:24:38 +0900"
    }
  ]
}