{
  "source": "NHKONEニュース",
  "updated": "2026-01-14T07:03:16.954Z",
  "items": [
    {
      "title": "株価 5万4000円超え 終値の最高値を更新",
      "link": "https://news.web.nhk/newsweb/na/na-k10015025861000",
      "pubDate": "Wed, 14 Jan 2026 15:45:07 +0900"
    },
    {
      "title": "高市首相 夕方にも与党幹部と会談へ 衆院解散の意向を伝達か",
      "link": "https://news.web.nhk/newsweb/na/na-k10015025901000",
      "pubDate": "Wed, 14 Jan 2026 14:08:50 +0900"
    },
    {
      "title": "浜岡原発 審査を当面停止 地震想定の過小評価疑い受け 規制委",
      "link": "https://news.web.nhk/newsweb/na/na-k10015025951000",
      "pubDate": "Wed, 14 Jan 2026 14:22:20 +0900"
    },
    {
      "title": "群馬 3人死亡事故初公判 元運転手 危険運転の起訴内容否認",
      "link": "https://news.web.nhk/newsweb/na/na-k10015025991000",
      "pubDate": "Wed, 14 Jan 2026 13:08:52 +0900"
    },
    {
      "title": "タイ東北部で建設用クレーンが走行中の列車直撃 12人死亡",
      "link": "https://news.web.nhk/newsweb/na/na-k10015026181000",
      "pubDate": "Wed, 14 Jan 2026 14:38:45 +0900"
    },
    {
      "title": "皇居で新春恒例「歌会始」 お題は「明」",
      "link": "https://news.web.nhk/newsweb/na/na-k10015025981000",
      "pubDate": "Wed, 14 Jan 2026 13:00:22 +0900"
    },
    {
      "title": "劇団員女性ひき逃げ事件 白タク行為か 会社の当時の社長逮捕",
      "link": "https://news.web.nhk/newsweb/na/na-k10015026091000",
      "pubDate": "Wed, 14 Jan 2026 13:05:29 +0900"
    }
  ]
}