{
  "source": "NHKONEニュース",
  "updated": "2026-01-30T05:55:39.003Z",
  "items": [
    {
      "title": "東京 4億円強盗事件 香港に輸送のため車積み込み中 襲われたか",
      "link": "https://news.web.nhk/newsweb/na/na-k10015039291000",
      "pubDate": "Fri, 30 Jan 2026 11:55:58 +0900"
    },
    {
      "title": "トランプ大統領 カナダで製造の航空機 認証取り消す意向示す",
      "link": "https://news.web.nhk/newsweb/na/na-k10015039511000",
      "pubDate": "Fri, 30 Jan 2026 14:35:25 +0900"
    },
    {
      "title": "JR常磐線 全線で運転を再開 上野駅で架線が切れた影響",
      "link": "https://news.web.nhk/newsweb/na/na-k10015039531000",
      "pubDate": "Fri, 30 Jan 2026 14:11:10 +0900"
    },
    {
      "title": "日本海側中心に雪 平年2倍超の積雪の地域も 空の便にも影響",
      "link": "https://news.web.nhk/newsweb/na/na-k10015038941000",
      "pubDate": "Fri, 30 Jan 2026 11:52:50 +0900"
    },
    {
      "title": "トランプ大統領 ロシアにキーウなど攻撃停止を要請 厳寒理由に",
      "link": "https://news.web.nhk/newsweb/na/na-k10015039501000",
      "pubDate": "Fri, 30 Jan 2026 14:01:05 +0900"
    },
    {
      "title": "日本で働く外国人 去年257万人余 初めて250万人超える 厚労省",
      "link": "https://news.web.nhk/newsweb/na/na-k10015039471000",
      "pubDate": "Fri, 30 Jan 2026 14:02:49 +0900"
    },
    {
      "title": "歌舞伎町ホスト逮捕 マッチングアプリを悪用し女性客引きか",
      "link": "https://news.web.nhk/newsweb/na/na-k10015039491000",
      "pubDate": "Fri, 30 Jan 2026 14:12:49 +0900"
    }
  ]
}