{
  "source": "NHKONEニュース",
  "updated": "2026-02-02T23:07:50.398Z",
  "items": [
    {
      "title": "トランプ大統領 グラミー賞司会者を提訴の考え ジョークに激怒",
      "link": "https://news.web.nhk/newsweb/na/na-k10015042001000",
      "pubDate": "Tue, 03 Feb 2026 04:35:13 +0900"
    },
    {
      "title": "日本海側で雪降り続く 青森県など積雪が平年を大幅に上回る",
      "link": "https://news.web.nhk/newsweb/na/na-k10015041921000",
      "pubDate": "Tue, 03 Feb 2026 05:59:27 +0900"
    },
    {
      "title": "米特使とイラン外相 6日に会談か 核施設攻撃以降で初 米報道",
      "link": "https://news.web.nhk/newsweb/na/na-k10015042011000",
      "pubDate": "Tue, 03 Feb 2026 06:23:31 +0900"
    },
    {
      "title": "米 インドの追加関税引き下げへ ロシア産原油輸入停止同意で",
      "link": "https://news.web.nhk/newsweb/na/na-k10015042051000",
      "pubDate": "Tue, 03 Feb 2026 06:31:45 +0900"
    },
    {
      "title": "NYダウ 515ドル値上がり 製造業の景況感 市場予想大きく上回る",
      "link": "https://news.web.nhk/newsweb/na/na-k10015042071000",
      "pubDate": "Tue, 03 Feb 2026 06:46:57 +0900"
    },
    {
      "title": "衆院選 投票日まで残り5日 各党が重点選挙区を絞り支持拡大へ",
      "link": "https://news.web.nhk/newsweb/na/na-k10015041961000",
      "pubDate": "Tue, 03 Feb 2026 02:31:22 +0900"
    },
    {
      "title": "広島の羽月選手 逮捕時も “ゾンビたばこ”エトミデート所持か",
      "link": "https://news.web.nhk/newsweb/na/na-k10015041951000",
      "pubDate": "Tue, 03 Feb 2026 05:07:11 +0900"
    }
  ]
}