{
  "source": "NHKONEニュース",
  "updated": "2026-02-22T01:17:21.069Z",
  "items": [
    {
      "title": "トランプ大統領 “10％の新たな関税 税率を15％に引き上げる”",
      "link": "https://news.web.nhk/newsweb/na/na-k10015058381000",
      "pubDate": "Sun, 22 Feb 2026 05:46:47 +0900"
    },
    {
      "title": "岡山 「裸祭り」で複数の男性が病院に搬送 うち3人が意識なし",
      "link": "https://news.web.nhk/newsweb/na/na-k10015058351000",
      "pubDate": "Sun, 22 Feb 2026 05:30:16 +0900"
    },
    {
      "title": "フィギュアスケート エキシビション 選手たちが観客魅了 五輪",
      "link": "https://news.web.nhk/newsweb/na/na-k10015058421000",
      "pubDate": "Sun, 22 Feb 2026 08:33:33 +0900"
    },
    {
      "title": "千葉 睦沢町で住宅火災 2人けが 小学生2人含む3人と連絡取れず",
      "link": "https://news.web.nhk/newsweb/na/na-k10015058441000",
      "pubDate": "Sun, 22 Feb 2026 09:40:51 +0900"
    },
    {
      "title": "坂本花織 五輪ラストダンスは“感謝の舞い” エキシビション",
      "link": "https://news.web.nhk/newsweb/na/na-k10015058461000",
      "pubDate": "Sun, 22 Feb 2026 10:03:59 +0900"
    },
    {
      "title": "国連 ウクライナ女性を支援する団体への援助 各国に継続を訴え",
      "link": "https://news.web.nhk/newsweb/na/na-k10015058391000",
      "pubDate": "Sun, 22 Feb 2026 05:42:52 +0900"
    },
    {
      "title": "高木美帆 “揺れる感情の中で” 五輪全種目終え会見【動画も】",
      "link": "https://news.web.nhk/newsweb/na/na-k10015058171000",
      "pubDate": "Sun, 22 Feb 2026 01:13:49 +0900"
    }
  ]
}