{
  "source": "NHKONEニュース",
  "updated": "2026-03-10T05:08:09.410Z",
  "items": [
    {
      "title": "岐阜 可児 大王製紙の工場で作業員6人が救急搬送",
      "link": "https://news.web.nhk/newsweb/na/na-k10015071621000",
      "pubDate": "Tue, 10 Mar 2026 12:03:35 +0900"
    },
    {
      "title": "富山 2人死亡の衝突事故 逮捕の会社員は時速約140キロで走行か",
      "link": "https://news.web.nhk/newsweb/na/na-k10015071671000",
      "pubDate": "Tue, 10 Mar 2026 13:39:45 +0900"
    },
    {
      "title": "北海道 上富良野町 雪崩に男性1人が巻き込まれたか 警察",
      "link": "https://news.web.nhk/newsweb/na/na-k10015071591000",
      "pubDate": "Tue, 10 Mar 2026 13:47:35 +0900"
    },
    {
      "title": "楽天モバイル不正契約 IDなど約500万件保存 仲間と方法共有か",
      "link": "https://news.web.nhk/newsweb/na/na-k10015071641000",
      "pubDate": "Tue, 10 Mar 2026 13:32:42 +0900"
    },
    {
      "title": "トランプ大統領「イランが石油流通止めれば20倍激しく攻撃」",
      "link": "https://news.web.nhk/newsweb/na/na-k10015071331000",
      "pubDate": "Tue, 10 Mar 2026 12:27:54 +0900"
    },
    {
      "title": "関東で積雪 東京23区でも雪やみぞれ 交通影響に警戒を",
      "link": "https://news.web.nhk/newsweb/na/na-k10015071511000",
      "pubDate": "Tue, 10 Mar 2026 12:10:20 +0900"
    },
    {
      "title": "政府 パスポート申請手数料引き下げなど旅券法改正案 閣議決定",
      "link": "https://news.web.nhk/newsweb/na/na-k10015071461000",
      "pubDate": "Tue, 10 Mar 2026 12:42:27 +0900"
    }
  ]
}