{
  "source": "NHKONEニュース",
  "updated": "2026-04-26T04:33:28.203Z",
  "items": [
    {
      "title": "トランプ氏出席の夕食会で発砲か「発砲者は確保」とSNSに投稿",
      "link": "https://news.web.nhk/newsweb/na/na-k10015108571000",
      "pubDate": "Sun, 26 Apr 2026 13:24:38 +0900"
    },
    {
      "title": "岩手 大槌町の山林火災 約1373ヘクタールが焼ける",
      "link": "https://news.web.nhk/newsweb/na/na-k10015108391000",
      "pubDate": "Sun, 26 Apr 2026 13:25:32 +0900"
    },
    {
      "title": "日韓両政府 次官級「2プラス2」来月初開催へ 安保協力強化図る",
      "link": "https://news.web.nhk/newsweb/na/na-k10015108591000",
      "pubDate": "Sun, 26 Apr 2026 13:05:16 +0900"
    },
    {
      "title": "サッカー ACLエリート 町田ゼルビア 延長の末0対1で敗れ準優勝",
      "link": "https://news.web.nhk/newsweb/na/na-k10015108581000",
      "pubDate": "Sun, 26 Apr 2026 12:54:09 +0900"
    },
    {
      "title": "北海道・三陸沖後発地震注意情報 引き続き日頃の備え確認を",
      "link": "https://news.web.nhk/newsweb/na/na-k10015108491000",
      "pubDate": "Sun, 26 Apr 2026 11:55:34 +0900"
    },
    {
      "title": "ロシア下院議長 北朝鮮訪問 ロシア派兵記念館開館式出席へ",
      "link": "https://news.web.nhk/newsweb/na/na-k10015108461000",
      "pubDate": "Sun, 26 Apr 2026 10:57:20 +0900"
    },
    {
      "title": "米特使ら派遣取りやめ トランプ大統領イラン側対応注視の姿勢",
      "link": "https://news.web.nhk/newsweb/na/na-k10015108471000",
      "pubDate": "Sun, 26 Apr 2026 11:33:39 +0900"
    }
  ]
}