{
  "source": "NHKONEニュース",
  "updated": "2026-03-13T16:50:00.288Z",
  "items": [
    {
      "title": "新年度予算案 衆院本会議で可決 自民・維新両党など賛成多数で",
      "link": "https://news.web.nhk/newsweb/na/na-k10015075271000",
      "pubDate": "Sat, 14 Mar 2026 00:42:17 +0900"
    },
    {
      "title": "東急東横線 みなとみらい線 9時間半運転見合わせ 12万人余影響",
      "link": "https://news.web.nhk/newsweb/na/na-k10015074741000",
      "pubDate": "Sat, 14 Mar 2026 00:26:07 +0900"
    },
    {
      "title": "モジタバ師 徹底抗戦の構え トランプ大統領 さらなる攻撃示唆",
      "link": "https://news.web.nhk/newsweb/na/na-k10015074571000",
      "pubDate": "Sat, 14 Mar 2026 01:42:44 +0900"
    },
    {
      "title": "パラ アルペン銀2個の村岡桃佳が会見「自分をほめていいかな」",
      "link": "https://news.web.nhk/newsweb/na/na-k10015075451000",
      "pubDate": "Sat, 14 Mar 2026 00:52:02 +0900"
    },
    {
      "title": "パラ アルペン男子大回転 鈴木猛史4位 森井大輝7位",
      "link": "https://news.web.nhk/newsweb/na/na-k10015075471000",
      "pubDate": "Sat, 14 Mar 2026 01:32:38 +0900"
    },
    {
      "title": "柏崎刈羽原発6号機で発送電停止させると発表 原子炉に異常なし",
      "link": "https://news.web.nhk/newsweb/na/na-k10015075211000",
      "pubDate": "Fri, 13 Mar 2026 22:22:31 +0900"
    },
    {
      "title": "2026年度のNHK予算 衆院本会議で賛成多数で承認",
      "link": "https://news.web.nhk/newsweb/na/na-k10015075331000",
      "pubDate": "Fri, 13 Mar 2026 22:30:18 +0900"
    }
  ]
}