{
  "source": "NHKONEニュース",
  "updated": "2026-04-02T01:25:22.234Z",
  "items": [
    {
      "title": "【速報中】トランプ大統領が演説“圧倒的な勝利を収めてきた”",
      "link": "https://news.web.nhk/newsweb/na/na-k10015090401000",
      "pubDate": "Thu, 02 Apr 2026 10:22:52 +0900"
    },
    {
      "title": "【地震速報】宮城と福島で震度３ 津波の心配なし",
      "link": "https://news.web.nhk/newsweb/na/na-k10015089611000",
      "pubDate": "Thu, 02 Apr 2026 09:59:52 +0900"
    },
    {
      "title": "「アルテミス計画」打ち上げ成功 人類 約半世紀ぶり月へ",
      "link": "https://news.web.nhk/newsweb/na/na-k10015090331000",
      "pubDate": "Thu, 02 Apr 2026 09:03:11 +0900"
    },
    {
      "title": "インドネシア付近 M7.4地震 日本は多少潮位変化も被害心配なし",
      "link": "https://news.web.nhk/newsweb/na/na-k10015090441000",
      "pubDate": "Thu, 02 Apr 2026 10:16:21 +0900"
    },
    {
      "title": "仏マクロン大統領にNW9広内キャスターが問う 国際社会での役割",
      "link": "https://news.web.nhk/newsweb/na/na-k10015089981000",
      "pubDate": "Wed, 01 Apr 2026 20:59:24 +0900"
    },
    {
      "title": "今年度予算案 参院 野党側“首相出席の集中審議が採決の条件”",
      "link": "https://news.web.nhk/newsweb/na/na-k10015090251000",
      "pubDate": "Thu, 02 Apr 2026 05:29:46 +0900"
    },
    {
      "title": "スペースX“株式の新規上場を申請 過去最大規模か” 米報道",
      "link": "https://news.web.nhk/newsweb/na/na-k10015090411000",
      "pubDate": "Thu, 02 Apr 2026 09:05:29 +0900"
    }
  ]
}