{
  "source": "NHKONEニュース",
  "updated": "2026-01-16T11:10:20.124Z",
  "items": [
    {
      "title": "JR山手線の停電トラブル 67万人余に影響 感電防止装置に不具合",
      "link": "https://news.web.nhk/newsweb/na/na-k10015027701000",
      "pubDate": "Fri, 16 Jan 2026 19:29:42 +0900"
    },
    {
      "title": "立民・公明の新党 名称は「中道改革連合」に",
      "link": "https://news.web.nhk/newsweb/na/na-k10015027771000",
      "pubDate": "Fri, 16 Jan 2026 18:57:30 +0900"
    },
    {
      "title": "プルデンシャル生命 社員ら100人余が顧客から31億円不適切受領",
      "link": "https://news.web.nhk/newsweb/na/na-k10015028001000",
      "pubDate": "Fri, 16 Jan 2026 17:52:36 +0900"
    },
    {
      "title": "山梨 山林火災 大月市が138世帯に新たに避難指示",
      "link": "https://news.web.nhk/newsweb/na/na-k10015028471000",
      "pubDate": "Fri, 16 Jan 2026 19:08:41 +0900"
    },
    {
      "title": "衆院選へ急ピッチで準備進む 真冬・受験シーズンで懸念も…",
      "link": "https://news.web.nhk/newsweb/na/na-k10015028501000",
      "pubDate": "Fri, 16 Jan 2026 19:33:39 +0900"
    },
    {
      "title": "衆院解散めぐり 高市内閣 閣僚から発言相次ぐ",
      "link": "https://news.web.nhk/newsweb/na/na-k10015027881000",
      "pubDate": "Fri, 16 Jan 2026 15:09:50 +0900"
    },
    {
      "title": "阪神・淡路大震災から17日で31年 神戸で追悼のつどい始まる",
      "link": "https://news.web.nhk/newsweb/na/na-k10015027871000",
      "pubDate": "Fri, 16 Jan 2026 19:55:57 +0900"
    }
  ]
}